README.rst
setup.py
interactive_shell/__init__.py
interactive_shell.egg-info/PKG-INFO
interactive_shell.egg-info/SOURCES.txt
interactive_shell.egg-info/dependency_links.txt
interactive_shell.egg-info/top_level.txt